taolue_multi_retrival/__init__.py
taolue_multi_retrival/conf.py
taolue_multi_retrival/find_max_info.py
taolue_multi_retrival/multi_retrieve.py
taolue_multi_retrival/retriever.py
taolue_multi_retrival/util.py
taolue_multi_retrival-1.0.9.dist-info/METADATA
taolue_multi_retrival-1.0.9.dist-info/WHEEL
taolue_multi_retrival-1.0.9.dist-info/top_level.txt
taolue_multi_retrival-1.0.9.dist-info/RECORD
