Metadata-Version: 2.1
Name: taolue_multi_retrival
Version: 1.0.9
Summary: 韬略问答Agent多跳策略的多轮检索模块
Author: zhaowang
Author-email: zhaowang@stonehg.com
Requires-Python: >=3.10
Requires-Dist: jieba
Requires-Dist: loguru
Requires-Dist: Requests
Requires-Dist: retrying
Requires-Dist: setuptools
Requires-Dist: transformers
